acs_classifex/__init__.py
acs_classifex/ner_model.py
acs_classifex-0.1.0.dist-info/METADATA
acs_classifex-0.1.0.dist-info/WHEEL
acs_classifex-0.1.0.dist-info/top_level.txt
acs_classifex-0.1.0.dist-info/RECORD
