Metadata-Version: 2.1
Name: acs_classifex
Version: 0.1.0
Summary: A Python package for training a custom NER model using spaCy
Home-page: https://github.com/godhorus/acs_classifex
Author: ACS
Author-email: sanketgadge13@gmail.com
Classifier: Programming Language :: Python :: 3
Classifier: License :: OSI Approved :: MIT License
Classifier: Operating System :: OS Independent
Requires-Python: >=3.6
Requires-Dist: spacy>=3.0.0
